{
  "meta": {
    "requete_cible": "contrôle eclairage voiture gratuit",
    "date_analyse": "2025-11-21T16:14:00.724212",
    "language": "fr",
    "analyses_totales": 1
  },
  "syntheses_strategiques": {
    "analysis_2": {
      "analyse_angles_concurrentiels": {
        "angles_dominants": [
          {
            "angle": "Partenariat institutionnel multisectoriel pour prévention sécurité routière",
            "frequence_utilisation": "Positions 3 et 7",
            "niveau_profondeur_moyen": "approfondi",
            "positionnement_requis": "Obligatoire",
            "exemples_reussis": [
              "Position 3: Article Prévention Routière",
              "Position 7: Article sécurité routière"
            ]
          },
          {
            "angle": "Campagne saisonnière avec urgence temporelle",
            "frequence_utilisation": "Positions 3, 5 et 7",
            "niveau_profondeur_moyen": "modere",
            "positionnement_requis": "Recommande",
            "exemples_reussis": [
              "Position 3: Opération jusqu'à fin octobre",
              "Position 5: Événement localisé Caen"
            ]
          }
        ],
        "angles_emergents": [
          {
            "angle": "Impact vibrations route sur réglage feux",
            "utilise_par": "Position 3 uniquement",
            "potentiel_differentiation": "Thème technique peu exploité expliquant scientifiquement la nécessité des contrôles annuels",
            "difficulte_execution": "faible"
          },
          {
            "angle": "Phénomène éblouissement sécurité nocturne",
            "utilise_par": "Position 3 uniquement",
            "potentiel_differentiation": "Problème concret de conduite nocturne peu traité dans les contenus grand public",
            "difficulte_execution": "moyenne"
          }
        ]
      },
      "themes_obligatoires": [
        {
          "theme": "Réseau de centres partenaires et accessibilité géographique",
          "present_chez": [
            3,
            7
          ],
          "niveau_minimum_requis": "approfondi",
          "profondeur_observee": "Mention de 231 centres Carglass + 400 garages CNPA avec couverture territoriale",
          "justification": "Présent dans 100% des articles pertinents, essentiel pour l'actionnabilité"
        },
        {
          "theme": "Données statistiques sécurité nocturne",
          "present_chez": [
            3,
            7
          ],
          "niveau_minimum_requis": "modere",
          "profondeur_observee": "44% d'accidents mortels pour 10% du trafic, 1/2 automobiliste gêné la nuit",
          "justification": "Crédibilise l'offre et justifie la nécessité des contrôles"
        },
        {
          "theme": "Période de validité et urgence temporelle",
          "present_chez": [
            3,
            5,
            7
          ],
          "niveau_minimum_requis": "modere",
          "profondeur_observee": "Opération limitée dans le temps (jusqu'à fin octobre)",
          "justification": "Crée un sentiment d'urgence et motive l'action immédiate"
        }
      ],
      "themes_emergents_consolides": [
        {
          "theme": "Impact vibrations route sur alignement phares",
          "articles_mentionnant": [
            3
          ],
          "frequence_apparition": "10% du SERP",
          "niveau_traitement_observe": "modere",
          "opportunite_differentiation": "Explication scientifique unique justifiant la nécessité des contrôles annuels",
          "potentiel_seo": "eleve",
          "justification_potentiel": "Répond à une question technique spécifique avec fort potentiel longue traîne",
          "recommandation_exploitation": "Développer un guide technique sur l'entretien préventif des phares",
          "complexite_execution": "faible"
        },
        {
          "theme": "Problématique éblouissement conduite nocturne",
          "articles_mentionnant": [
            3
          ],
          "frequence_apparition": "10% du SERP",
          "niveau_traitement_observe": "superficiel",
          "opportunite_differentiation": "Angle sécurité concret centré sur l'expérience utilisateur réelle",
          "potentiel_seo": "moyen",
          "justification_potentiel": "Thème engageant qui touche directement le confort de conduite",
          "recommandation_exploitation": "Contenu expert sur les techniques anti-éblouissement",
          "complexite_execution": "moyenne"
        }
      ],
      "themes_a_exclure_consolides": [
        {
          "theme": "Présentation générale services auto génériques",
          "distribution_serp": {
            "present_top5": [],
            "present_positions_6_10": [
              2,
              4,
              6
            ]
          },
          "raison_exclusion": "saturation",
          "justification_exclusion": "Contenu commercial générique sans pertinence pour la requête, corrélé avec mauvais positionnement",
          "correlation_mauvais_positionnement": "100% des articles hors-sujet utilisent cet angle",
          "alternative_recommandee": "Focus exclusif sur l'offre spécifique de contrôle gratuit"
        },
        {
          "theme": "Événementiel local trop restreint",
          "distribution_serp": {
            "present_top5": [
              5
            ],
            "present_positions_6_10": []
          },
          "raison_exclusion": "dilution",
          "justification_exclusion": "Limite la portée nationale et l'utilité générale du contenu",
          "correlation_mauvais_positionnement": "Article position 5 jugé hors-sujet partiel pour limitation géographique",
          "alternative_recommandee": "Approche nationale avec possibilité de déclinaisons locales"
        }
      ],
      "opportunites_angles_uniques": [
        {
          "angle_propose": "Guide complet d'autodiagnostic des phares avant contrôle professionnel",
          "justification": "Absent chez tous les concurrents, répond au besoin d'autonomie et préparation avant déplacement",
          "niveau_ambition": "modere",
          "valeur_ajoutee_estimee": "Augmentation engagement utilisateur et positionnement sur requêtes complémentaires",
          "complexite_execution": "faible"
        },
        {
          "angle_propose": "Analyse comparative des différentes technologies d'éclairage (halogène, LED, xénon)",
          "justification": "Aucun concurrent n'aborde l'aspect technologique et les spécificités de réglage selon le type de phare",
          "niveau_ambition": "ambitieux",
          "valeur_ajoutee_estimee": "Positionnement en tant qu'expert technique et couverture requêtes spécifiques",
          "complexite_execution": "moyenne"
        }
      ],
      "gaps_concurrentiels": [
        {
          "gap_identifie": "Manque de détails procéduraux sur le déroulement concret du contrôle",
          "type": "actionabilite",
          "potentiel_seo": "eleve",
          "recommandation_exploitation": "Décrire étape par étape ce qui est vérifié pendant un contrôle d'éclairage"
        },
        {
          "gap_identifie": "Absence d'informations sur la gratuité réelle (ce qui est inclus/exclu)",
          "type": "profondeur",
          "potentiel_seo": "moyen",
          "recommandation_exploitation": "Préciser clairement le périmètre de gratuité et éventuels coûts supplémentaires"
        }
      ],
      "angles_a_exclure": [
        {
          "angle_declasse": "Page événementielle générale sans focus spécifique",
          "present_dans_positions": [
            1
          ],
          "absent_top5_mais_present_bas_classement": false,
          "raison_exclusion": "Dilution complète du message principal, hors sujet total",
          "risque_positionnement": "Très élevé - pénalité contenu non pertinent"
        },
        {
          "angle_declasse": "Landing page commerciale générique sans information spécifique",
          "present_dans_positions": [
            2,
            4
          ],
          "absent_top5_mais_present_bas_classement": false,
          "raison_exclusion": "Approche purement commerciale sans valeur informative",
          "risque_positionnement": "Élevé - faible valeur ajoutée pour l'utilisateur"
        }
      ],
      "strategie_positionnement": {
        "socle_obligatoire": {
          "angles_minimum": [
            "Partenariat institutionnel multisectoriel",
            "Campagne saisonnière avec urgence temporelle"
          ],
          "profondeur_requise": "approfondi",
          "themes_incontournables": [
            "Réseau de centres partenaires",
            "Données statistiques sécurité",
            "Période de validité"
          ]
        },
        "differentiation_recommandee": {
          "angles_uniques_proposes": [
            "Guide d'autodiagnostic des phares",
            "Analyse comparative technologies éclairage"
          ],
          "approfondissements_cibles": [
            "Impact vibrations sur réglage",
            "Problématique éblouissement"
          ],
          "approches_innovantes": [
            "Contenu interactif de pré-diagnostic",
            "Cartographie dynamique des centres"
          ],
          "themes_emergents_a_exploiter": [
            "Impact vibrations route",
            "Phénomène éblouissement"
          ]
        },
        "niveau_ambition_global": "ambitieux",
        "effort_editorial_estime": "Élevé - nécessite recherche technique approfondie et partenariats institutionnels"
      },
      "recommandation_positionnement_global": {
        "type_contenu_optimal": "Guide complet informatif avec éléments actionnables",
        "intention_cible": "informationnelle",
        "portee_commerciale_recommandee": "legere",
        "orientation_cta_optimale": "Redirection vers centres partenaires avec transparence sur gratuité"
      }
    }
  },
  "angle_select": {
    "angle_selectionne": "Guide complet d'autodiagnostic des phares avant contrôle professionnel",
    "score_total": "10/12",
    "justification_selection": "Cet angle comble parfaitement le besoin d'autonomie avant le contrôle gratuit tout en étant totalement complémentaire du socle institutionnel existant.",
    "scores_details": {
      "alignement_intention": "3/3",
      "non_redondance": "3/3",
      "valeur_ajoutee": "3/3",
      "faisabilite_roi": "1/3"
    }
  }
}